Metadata-Version: 1.0
Name: gausbin-distributions
Version: 0.1
Summary: Gaussian and Binomial distributions
Home-page: UNKNOWN
Author: UNKNOWN
Author-email: mounikavas@gmail.com
License: UNKNOWN
Platform: UNKNOWN
